groupdocs_comparison_cloud/__init__.py
groupdocs_comparison_cloud/api_client.py
groupdocs_comparison_cloud/api_exception.py
groupdocs_comparison_cloud/auth.py
groupdocs_comparison_cloud/configuration.py
groupdocs_comparison_cloud/rest.py
groupdocs_comparison_cloud/apis/__init__.py
groupdocs_comparison_cloud/apis/compare_api.py
groupdocs_comparison_cloud/apis/file_api.py
groupdocs_comparison_cloud/apis/folder_api.py
groupdocs_comparison_cloud/apis/info_api.py
groupdocs_comparison_cloud/apis/license_api.py
groupdocs_comparison_cloud/apis/preview_api.py
groupdocs_comparison_cloud/apis/review_api.py
groupdocs_comparison_cloud/apis/storage_api.py
groupdocs_comparison_cloud/models/__init__.py
groupdocs_comparison_cloud/models/apply_revisions_options.py
groupdocs_comparison_cloud/models/change_info.py
groupdocs_comparison_cloud/models/comparison_options.py
groupdocs_comparison_cloud/models/consumption_result.py
groupdocs_comparison_cloud/models/diagram_master_setting.py
groupdocs_comparison_cloud/models/disc_usage.py
groupdocs_comparison_cloud/models/error.py
groupdocs_comparison_cloud/models/error_details.py
groupdocs_comparison_cloud/models/file_info.py
groupdocs_comparison_cloud/models/file_version.py
groupdocs_comparison_cloud/models/file_versions.py
groupdocs_comparison_cloud/models/files_list.py
groupdocs_comparison_cloud/models/files_upload_result.py
groupdocs_comparison_cloud/models/format.py
groupdocs_comparison_cloud/models/formats_result.py
groupdocs_comparison_cloud/models/info_result.py
groupdocs_comparison_cloud/models/items_style.py
groupdocs_comparison_cloud/models/link.py
groupdocs_comparison_cloud/models/metadata.py
groupdocs_comparison_cloud/models/object_exist.py
groupdocs_comparison_cloud/models/page_info.py
groupdocs_comparison_cloud/models/preview_options.py
groupdocs_comparison_cloud/models/rectangle.py
groupdocs_comparison_cloud/models/revision_info.py
groupdocs_comparison_cloud/models/settings.py
groupdocs_comparison_cloud/models/size.py
groupdocs_comparison_cloud-25.11.dist-info/licenses/LICENSE
groupdocs_comparison_cloud-25.11.dist-info/METADATA
groupdocs_comparison_cloud-25.11.dist-info/WHEEL
groupdocs_comparison_cloud-25.11.dist-info/top_level.txt
groupdocs_comparison_cloud-25.11.dist-info/RECORD
